{
  "seed": 1234,
  "style_id": 57,
  "created_at": "2026-02-27T18:50:06.431235+00:00",
  "bbox": {
    "xmin": -4,
    "xmax": 29,
    "ymin": 3,
    "ymax": 28,
    "zmin": -4,
    "zmax": 27
  },
  "palette": "fortress",
  "style": "temple_rectangle_sawtooth_corner_mid_mix_v057",
  "image_size": {
    "width": 960,
    "height": 540
  },
  "camera_planner": {
    "radius": 43.2111,
    "target": {
      "x": 13.0,
      "y": 16.0,
      "z": 12.0
    },
    "fov": 70.0
  },
  "generation": {
    "origin": {
      "x": 0,
      "y": 4,
      "z": 0
    },
    "num_blocks": 5288,
    "stable_non_air_count": 5288
  },
  "views": [
    {
      "path": "images/rgb_view00_yaw+090.00_pitch+000.69.png",
      "x": 56.2111,
      "y": 16.52,
      "z": 12.0,
      "yaw": 90.0,
      "pitch": 0.6895,
      "fov": 70.0,
      "width": 960,
      "height": 540,
      "actual_x": 56.211,
      "actual_y": 16.52,
      "actual_z": 12.0
    },
    {
      "path": "images/rgb_view01_yaw+126.00_pitch+008.22.png",
      "x": 47.9585,
      "y": 22.24,
      "z": 37.3988,
      "yaw": 126.0,
      "pitch": 8.2171,
      "fov": 70.0,
      "width": 960,
      "height": 540,
      "actual_x": 47.958,
      "actual_y": 22.24,
      "actual_z": 37.399
    },
    {
      "path": "images/rgb_view02_yaw+162.00_pitch+000.69.png",
      "x": 26.353,
      "y": 16.52,
      "z": 53.0962,
      "yaw": 162.0,
      "pitch": 0.6895,
      "fov": 70.0,
      "width": 960,
      "height": 540,
      "actual_x": 26.353,
      "actual_y": 16.52,
      "actual_z": 53.096
    },
    {
      "path": "images/rgb_view03_yaw-162.00_pitch+008.22.png",
      "x": -0.353,
      "y": 22.24,
      "z": 53.0962,
      "yaw": -162.0,
      "pitch": 8.2171,
      "fov": 70.0,
      "width": 960,
      "height": 540,
      "actual_x": -0.353,
      "actual_y": 22.24,
      "actual_z": 53.096
    },
    {
      "path": "images/rgb_view04_yaw-126.00_pitch+000.69.png",
      "x": -21.9585,
      "y": 16.52,
      "z": 37.3988,
      "yaw": -126.0,
      "pitch": 0.6895,
      "fov": 70.0,
      "width": 960,
      "height": 540,
      "actual_x": -21.958,
      "actual_y": 16.52,
      "actual_z": 37.399
    },
    {
      "path": "images/rgb_view05_yaw-090.00_pitch+008.22.png",
      "x": -30.2111,
      "y": 22.24,
      "z": 12.0,
      "yaw": -90.0,
      "pitch": 8.2171,
      "fov": 70.0,
      "width": 960,
      "height": 540,
      "actual_x": -30.211,
      "actual_y": 22.24,
      "actual_z": 12.0
    },
    {
      "path": "images/rgb_view06_yaw-054.00_pitch+000.69.png",
      "x": -21.9585,
      "y": 16.52,
      "z": -13.3988,
      "yaw": -54.0,
      "pitch": 0.6895,
      "fov": 70.0,
      "width": 960,
      "height": 540,
      "actual_x": -21.958,
      "actual_y": 16.52,
      "actual_z": -13.399
    },
    {
      "path": "images/rgb_view07_yaw-018.00_pitch+008.22.png",
      "x": -0.353,
      "y": 22.24,
      "z": -29.0962,
      "yaw": -18.0,
      "pitch": 8.2171,
      "fov": 70.0,
      "width": 960,
      "height": 540,
      "actual_x": -0.353,
      "actual_y": 22.24,
      "actual_z": -29.096
    },
    {
      "path": "images/rgb_view08_yaw+018.00_pitch+000.69.png",
      "x": 26.353,
      "y": 16.52,
      "z": -29.0962,
      "yaw": 18.0,
      "pitch": 0.6895,
      "fov": 70.0,
      "width": 960,
      "height": 540,
      "actual_x": 26.353,
      "actual_y": 16.52,
      "actual_z": -29.096
    },
    {
      "path": "images/rgb_view09_yaw+054.00_pitch+008.22.png",
      "x": 47.9585,
      "y": 22.24,
      "z": -13.3988,
      "yaw": 54.0,
      "pitch": 8.2171,
      "fov": 70.0,
      "width": 960,
      "height": 540,
      "actual_x": 47.958,
      "actual_y": 22.24,
      "actual_z": -13.399
    },
    {
      "path": "images/rgb_view10_yaw+090.00_pitch+076.77.png",
      "x": 23.2,
      "y": 59.4,
      "z": 12.0,
      "yaw": 90.0,
      "pitch": 76.7742,
      "fov": 70.0,
      "width": 960,
      "height": 540,
      "actual_x": 23.2,
      "actual_y": 59.4,
      "actual_z": 12.0
    },
    {
      "path": "images/rgb_view11_yaw-090.00_pitch+077.20.png",
      "x": 2.8,
      "y": 60.9,
      "z": 12.0,
      "yaw": -90.0,
      "pitch": 77.2012,
      "fov": 70.0,
      "width": 960,
      "height": 540,
      "actual_x": 2.8,
      "actual_y": 60.9,
      "actual_z": 12.0
    }
  ]
}